pyipcalc/__init__.py
pyipcalc/__main__.py
pyipcalc/calculator.py
pyipcalc/cli.py
pyipcalc/display.py
pyipcalc/main.py
pyipcalc/models.py
pyipcalc-0.1.2.dist-info/METADATA
pyipcalc-0.1.2.dist-info/WHEEL
pyipcalc-0.1.2.dist-info/entry_points.txt
pyipcalc-0.1.2.dist-info/top_level.txt
pyipcalc-0.1.2.dist-info/RECORD
