Metadata-Version: 2.4
Name: pyipcalc
Version: 0.1.2
Summary: A utility to calculate ipv4, ipv6 network information.
Project-URL: Homepage, https://github.com/fxyzbtc/pyipcalc
Project-URL: Repository, https://github.com/fxyzbtc/pyipcalc
Classifier: Programming Language :: Python :: 3
Classifier: Operating System :: OS Independent
Classifier: Topic :: Utilities
Requires-Python: >=3.12
Requires-Dist: loguru>=0.7.3
Requires-Dist: typer>=0.12.5
